setup.py
pulsetranslator/__init__.py
pulsetranslator/daemon.py
pulsetranslator/loghandler.py
pulsetranslator/messageparams.py
pulsetranslator/pulsetranslator.py
pulsetranslator/runservice.py
pulsetranslator/testconsumer.py
pulsetranslator/translatorexceptions.py
pulsetranslator/translatorqueues.py
pulsetranslator.egg-info/PKG-INFO
pulsetranslator.egg-info/SOURCES.txt
pulsetranslator.egg-info/dependency_links.txt
pulsetranslator.egg-info/entry_points.txt
pulsetranslator.egg-info/not-zip-safe
pulsetranslator.egg-info/requires.txt
pulsetranslator.egg-info/top_level.txt