Metadata-Version: 1.0
Name: pulsetranslator
Version: 0.1
Summary: Service for translating rawa buildbot pulse messages into a standard format
Home-page: http://hg.mozilla.org/users/jgriffin_mozilla.com/pulsetranslator
Author: Jonathan Griffin
Author-email: jgriffin@mozilla.com
License: MPL
Platform: UNKNOWN
